{"stats":{"minecraft:crafted":{"minecraft:oak_planks":24,"minecraft:crafting_table":1,"minecraft:wooden_pickaxe":1,"minecraft:furnace":1,"minecraft:stone_axe":1,"minecraft:oak_boat":1,"minecraft:stick":12,"minecraft:iron_ingot":15,"minecraft:iron_pickaxe":1,"minecraft:stone_pickaxe":1,"minecraft:torch":4},"minecraft:killed":{"minecraft:zombie":2},"minecraft:picked_up":{"minecraft:birch_log":2,"minecraft:crafting_table":5,"carved_wood:dark_oak_crafting_table":1,"minecraft:chicken":1,"minecraft:wooden_pickaxe":1,"minecraft:oak_log":16,"minecraft:dirt":74,"minecraft:iron_ingot":2,"minecraft:stone_pickaxe":1,"cobblemon:pink_mint_seeds":2,"cobblemon:oran_berry":10,"minecraft:mossy_stone_bricks":2,"minecraft:gray_bed":1,"minecraft:oak_planks":8,"minecraft:furnace":1,"minecraft:stick":2,"minecraft:raw_iron":22,"minecraft:sweet_berries":3,"minecraft:torch":3,"cobblemon:persim_berry":14,"minecraft:dark_oak_log":3,"minecraft:light_gray_bed":1,"minecraft:purple_bed":2,"cobblemon:poke_ball":7,"minecraft:stone_axe":1,"cobblemon:pink_mint_leaf":2,"cobblemon:blue_apricorn":1,"minecraft:coal":6,"minecraft:cobblestone":34},"minecraft:dropped":{"minecraft:mossy_stone_bricks":1,"minecraft:wooden_pickaxe":1},"minecraft:used":{"minecraft:stone_pickaxe":27,"minecraft:wooden_pickaxe":18,"minecraft:torch":3,"minecraft:dirt":45,"minecraft:crafting_table":4,"minecraft:dark_oak_log":1,"minecraft:iron_pickaxe":10,"minecraft:stone_axe":5,"minecraft:purple_bed":1,"minecraft:furnace":1,"minecraft:oak_boat":1},"minecraft:custom":{"minecraft:interact_with_furnace":7,"minecraft:mob_kills":2,"cobblemon:captured":1,"minecraft:interact_with_crafting_table":6,"minecraft:leave_game":2,"minecraft:time_since_death":36333,"minecraft:sleep_in_bed":1,"minecraft:time_since_rest":9929,"minecraft:waystone_activated":1,"minecraft:sprint_one_cm":191010,"minecraft:damage_taken":2256,"minecraft:walk_one_cm":93956,"cobblemon:level_up":2,"minecraft:drop":2,"minecraft:damage_dealt":301,"cobblemon:battles_total":3,"minecraft:swim_one_cm":32160,"minecraft:fly_one_cm":146321,"minecraft:open_chest":10,"minecraft:crouch_one_cm":3019,"minecraft:play_time":52806,"minecraft:deaths":1,"minecraft:sneak_time":806,"cobblemon:dex_entries":4,"minecraft:walk_under_water_one_cm":10148,"minecraft:boat_one_cm":260791,"minecraft:jump":1006,"cobblemon:battles_won":1,"minecraft:walk_on_water_one_cm":8389,"minecraft:total_world_time":52806,"minecraft:fall_one_cm":32176},"minecraft:mined":{"cobblemon:healing_machine":1,"minecraft:dark_oak_log":2,"cobblemon:pc":1,"minecraft:powder_snow":3,"minecraft:crafting_table":4,"minecraft:torch":3,"cobblemon:apricorn_leaves":7,"minecraft:short_grass":1,"minecraft:grass_block":4,"minecraft:light_gray_bed":1,"minecraft:redstone_wire":1,"minecraft:spruce_leaves":5,"minecraft:kelp":2,"minecraft:purple_bed":2,"minecraft:furnace":1,"minecraft:birch_log":2,"minecraft:iron_ore":21,"minecraft:gray_bed":1,"minecraft:oak_log":11,"minecraft:coal_ore":3,"minecraft:dirt":2,"minecraft:stone":22,"minecraft:mossy_stone_bricks":1,"minecraft:oak_leaves":1,"carved_wood:dark_oak_crafting_table":1},"minecraft:killed_by":{"cobblemon:pokemon":1}},"DataVersion":3955}